README.md
setup.py
FBWeb/__init__.py
FBWeb/models.py
FBWeb.egg-info/PKG-INFO
FBWeb.egg-info/SOURCES.txt
FBWeb.egg-info/dependency_links.txt
FBWeb.egg-info/top_level.txt