Metadata-Version: 1.0
Name: FBWeb
Version: 1.0
Summary: Simplicity-focused Flask website builder
Home-page: UNKNOWN
Author: Albert Szadziński
Author-email: albert.szadzinski@smcebi.edu.pl
License: GPL-3.0
Platform: UNKNOWN
